rocketbase/__init__.py
rocketbase/api.py
rocketbase/exceptions.py
rocketbase/rocket.py
rocketbase/shadowRocket.py
rocketbase/utils.py
rocketbase-0.4.0.dist-info/LICENSE.txt
rocketbase-0.4.0.dist-info/METADATA
rocketbase-0.4.0.dist-info/WHEEL
rocketbase-0.4.0.dist-info/top_level.txt
rocketbase-0.4.0.dist-info/RECORD
