Metadata-Version: 2.1
Name: rocketbase
Version: 0.4.0
Summary: Making Machine Learning available to everyone
Home-page: https://rocketbase.ai
Author: Mirage Technologies AG
Author-email: hello@mirage.id
License: Proprietary
Keywords: automatic,ML,deployment,pytorch,pretrained,API
Platform: UNKNOWN
Classifier: Development Status :: 3 - Alpha
Classifier: Intended Audience :: Developers
Classifier: Topic :: Software Development :: Build Tools
Classifier: Programming Language :: Python :: 3
Classifier: Programming Language :: Python :: 3.6
Classifier: Programming Language :: Python :: 3.7
Requires-Dist: tqdm
Requires-Dist: requests
Requires-Dist: google-cloud-storage
Requires-Dist: numpy (>=1.16.3)
Requires-Dist: opencv-python (>=4.1.0.25)
Requires-Dist: Pillow (>=6.0.0)
Requires-Dist: scikit-image (>=0.15.0)
Requires-Dist: scipy (>=1.2.1)
Requires-Dist: torch (>=1.0.1.post2)
Requires-Dist: torchvision (>=0.2.2.post3)
